[
    {
    "icon": "confianza",
    "Titulo": "Diseño Web",
    "description": "Descripción"
  },
  {
    "icon": "confianza",
    "Titulo": "Diseño Web",
    "description": "Descripción"
  },
  {
    "icon": "confianza",
    "Titulo": "Diseño Web",
    "description": "Descripción"
  },
  {
    "icon": "confianza",
    "Titulo": "Diseño Web",
    "description": "Descripción"
  },
  {
    "icon": "confianza",
    "Titulo": "Diseño Web",
    "description": "Descripción"
  },
  {
    "icon": "confianza",
    "Titulo": "Diseño Web",
    "description": "Descripción"
  }
]